<?xml version="1.0"?>
<root>
  <Pedidos id="19">
    <cedula>1542541256</cedula>
    <empleado>Pazmiño Jose Luis</empleado>
    <fecha_creacion>Vie. 10/02/2023</fecha_creacion>
    <rige_desde>Mié. 08/02/2023</rige_desde>
    <rige_hasta>Jue. 16/02/2023</rige_hasta>
    <numero_partida>5446464848</numero_partida>
  </Pedidos>
  <Pedidos id="17">
    <cedula>1717278210</cedula>
    <empleado>Robalino Lavayen Josue Larry</empleado>
    <fecha_creacion>Jue. 09/02/2023</fecha_creacion>
    <rige_desde>Mié. 15/02/2023</rige_desde>
    <rige_hasta>Mar. 28/02/2023</rige_hasta>
    <numero_partida>84984984894984</numero_partida>
  </Pedidos>
  <Pedidos id="21">
    <cedula>1725458291</cedula>
    <empleado>Pantoja Yumbo Luis Fernando</empleado>
    <fecha_creacion>Vie. 10/02/2023</fecha_creacion>
    <rige_desde>Mar. 14/02/2023</rige_desde>
    <rige_hasta/>
    <numero_partida>548448488848</numero_partida>
  </Pedidos>
  <Pedidos id="20">
    <cedula>1753595717</cedula>
    <empleado>Heredia Jhonatan</empleado>
    <fecha_creacion>Vie. 10/02/2023</fecha_creacion>
    <rige_desde>Mié. 15/02/2023</rige_desde>
    <rige_hasta/>
    <numero_partida>5777555775</numero_partida>
  </Pedidos>
  <Pedidos id="18">
    <cedula>1753595717</cedula>
    <empleado>Heredia Jhonatan</empleado>
    <fecha_creacion>Vie. 10/02/2023</fecha_creacion>
    <rige_desde>Mié. 15/02/2023</rige_desde>
    <rige_hasta>Mar. 28/02/2023</rige_hasta>
    <numero_partida>44451515151</numero_partida>
  </Pedidos>
</root>